README.md
setup.py
MetaOptim/__init__.py
MetaOptim/_functional.py
MetaOptim/meta_adam.py
MetaOptim/meta_optimizer.py
MetaOptim/meta_rmsprop.py
MetaOptim/meta_sgd.py
MetaOptim.egg-info/PKG-INFO
MetaOptim.egg-info/SOURCES.txt
MetaOptim.egg-info/dependency_links.txt
MetaOptim.egg-info/requires.txt
MetaOptim.egg-info/top_level.txt
test/testSampler.py
test/test_nn.py
test/test_nn_marl.py
test/test_relu.py