Metadata-Version: 2.1
Name: MetaOptim
Version: 0.0
Summary: A differentiable optimizer.
Home-page: https://github.com/metaopt/MetaOptim
Author: Jie Ren
Author-email: jieren9806@gmail.com
License: Apache License Version 2.0
Keywords: meta learning
Platform: UNKNOWN
